{
  "body": [
    {
      "text": "", 
      "align": "", 
      "textPos": "", 
      "img": "", 
      "title": ""
    }
  ], 
  "cate": "8", 
  "img": "html/20170904/K10011125981_1709041307_1709041335_01_03.jpg", 
  "title": "宮城 南三陸町 新しい役場庁舎で業務開始", 
  "datetime": "2017-09-04T11:32", 
  "duration": 61, 
  "video": "https://www3.nhk.or.jp/news/html/20170904/movie/k10011125981_201709041307_201709041334.html", 
  "date": "9æ4æ¥ 11æ32å", 
  "summary": "東日本大震災の津波で全壊し、６年半を経て再建された宮城県南三陸町の新しい役場庁舎で４日から業務が始まり、朝から住民が手続きなどで窓口を訪れています。", 
  "more": "宮城県南三陸町は震災の津波に襲われて役場の本庁舎や隣接する防災対策庁舎が全壊し、防災対策庁舎では情報収集などに当たっていた職員ら４３人が犠牲になったとされています。<br /><br />町は先週まで仮設庁舎で業務を続けてきましたが、以前の場所からおよそ１．５キロ離れた高台に新たな庁舎が完成し、４日から業務が始まりました。<br /><br />新しい庁舎では４日朝、職員たちが次々と出勤し、窓口業務が始まる直前まで住民票のシステムのチェックなどに追われました。午前８時すぎ、業務が始まると住民が訪れて手続きを進めていました。<br /><br />新しい庁舎は３階建てで震度７の揺れにも耐えられるよう設計されたほか、自家発電の装置や災害時の拠点になる「災害対策室」などが備えられています。<br /><br />訪れた住民の女性は「震災前の役場は低地の川沿いにあったので津波に襲われてしまいましたが、ここは頑丈なつくりで高台に建っているので避難もできて安心です」と話していました。<br />また職員の男性は「震災から６年半がたってやっとこの日が来たという思いです。復興に向けてより頑張って皆さんが利用しやすい役場にしていきたい」と話していました。"
}